axiomatik/__init__.py
axiomatik/axiomatik.py
axiomatik/axiomatikify.py
axiomatik/future_axiomatik.py
axiomatik/simple_axiomatik.py
axiomatik/simple_quick.py
axiomatik/simple_usage.py
axiomatik-0.2.2.dist-info/licenses/LICENSE
axiomatik-0.2.2.dist-info/METADATA
axiomatik-0.2.2.dist-info/WHEEL
axiomatik-0.2.2.dist-info/top_level.txt
axiomatik-0.2.2.dist-info/RECORD
