Metadata-Version: 2.4
Name: axiomatik
Version: 0.2.2
Summary: Axiomatik is a comprehensive runtime verification system that brings formal verification concepts to practical Python programming.
Home-page: https://github.com/SaxonRah/axiomatik
Author: SaxonRah
Author-email: paraboliclabs@gmail.com
Project-URL: Bug Tracker, https://github.com/SaxonRah/axiomatik/issues
Classifier: Programming Language :: Python :: 3
Classifier: License :: OSI Approved :: MIT License
Classifier: Operating System :: OS Independent
Requires-Python: >=3.8
License-File: LICENSE
Requires-Dist: click==8.2.1
Requires-Dist: libcst==1.8.2
Requires-Dist: matplotlib==3.10.5
Dynamic: author
Dynamic: author-email
Dynamic: classifier
Dynamic: description
Dynamic: description-content-type
Dynamic: home-page
Dynamic: license-file
Dynamic: project-url
Dynamic: requires-dist
Dynamic: requires-python
Dynamic: summary
